CHANGELOG.txt
LICENSE.txt
MANIFEST.in
README.txt
apple.png
player.png
setup.py
catengine.egg-info/SOURCES.txt
catengine.egg-info/dependency_links.txt
catengine.egg-info/requires.txt
catengine.egg-info/top_level.txt
examples/Snake/snake.py
examples/Snake/audio/death.wav
examples/Snake/audio/food_collect.wav
examples/Snake/audio/music.wav
realityengine/__init__.py
realityengine/audio.py
realityengine/game_object.py
realityengine/gui.py
realityengine/util.py
realityengine/window.py
realityengine.egg-info/PKG-INFO
realityengine.egg-info/SOURCES.txt
realityengine.egg-info/dependency_links.txt
realityengine.egg-info/requires.txt
realityengine.egg-info/top_level.txt
realityengine/images/icon.png