Metadata-Version: 2.1
Name: realityengine
Version: 1.2.0
Summary: realityengine is a game library designed to make game development with Python easy.
Home-page: 
Author: Nathaniel Chandler
Author-email: nchand05@outlook.com
License: MIT
Keywords: Python,Game Development,Educational
Classifier: Development Status :: 5 - Production/Stable
Classifier: Intended Audience :: Education
Classifier: Programming Language :: Python :: 3
Classifier: Programming Language :: Python :: 3.6
Classifier: Programming Language :: Python :: 3.7
Classifier: Programming Language :: Python :: 3.8
Classifier: Programming Language :: Python :: 3.9
Classifier: Programming Language :: Python :: 3.10
Classifier: Operating System :: Microsoft :: Windows
Classifier: Operating System :: POSIX
Classifier: Operating System :: Unix
Classifier: Operating System :: MacOS
License-File: LICENSE.txt
